{
  "login": {
    "url": "https://ssokeycloak-uat.zakipointhealth.com/realms/zakipoint-products/protocol/openid-connect/token"
  },
  "apis": [
    {
      "method": "POST",
      "url": "/api/eligibility/v2/checkEligibility",
      "payload": {
        "groupId":"COBALT_BBA",
        "providerTinOrNpi":"621861198",
        "patientDob":"07/07/1967",
        "memberIdOrSsnOrEmployeeId":"AVQ998400017-00"
      }
    },
    {
      "method": "POST",
      "url": "/api/eligibility/v2/check",
      "payload": {
        "groupId":"COBALT_BBA",
        "providerTinOrNpi":"050524568",
        "patientDob":"04/13/1976",
        "patientLastName":"MOULTON", 
        "patientFirstName":"AMY", 
        "memberIdOrSsn":"VNA982600021"
      }
    },
    {
      "method": "POST",
      "url": "/api/member/eligibilityFaxBack",
      "payload": {
        "groupId": "COBALT_BBA", 
        "divisionId": "80939", 
        "providerTin": "222667354", 
        "memberId": "3869a6e913637b3ac4929dd9f720444bcoba", 
        "claimCoverageCode": "DEN"
      }
    },
    {
      "method": "POST",
      "url": "/api/member/claimFaxBack",
      "payload": {
        "groupId": "COBALT_BBA",
        "divisionId": "80975",
        "memberId": "9a553ce97be637b491b273d5c428deb0coba",
        "providerTinOrNpi": "042800541",
        "serviceToDate": "07/24/2025",
        "serviceFromDate": "07/24/2025",
        "patientDob": "04/13/1980",
        "deliverTo": "9898877666"
      }
    },
    {
      "method": "POST",
      "url": "/api/claim/v2/check",
      "payload": {
        "groupId":"COBALT_BBA",
        "providerTinOrNpi":"042297845",
        "patientDob":"08/07/2017",
        "serviceFromDate":"11/04/2024",
        "serviceToDate":"11/04/2024",
        "memberIdOrSsn":"CTP999900092",
        "claimId":""
      }
    },
    {
      "method": "POST",
      "url": "/api/member/faxBackFullDoc",
      "payload": {
        "claimCoverageCode": "DEN",
        "divisionId": "80975",
        "groupId": "COBALT_BBA",
        "memberId": "9a553ce97be637b491b273d5c428deb0coba",
        "providerTin": "631217503"
      }
    },
    {
      "method": "POST",
      "url": "/api/member/idcard",
      "payload": {
        "divisionId": "81039",
        "employeeId": "X3FYQCN038TVB715NZ55FHA044",
        "groupId": "COBALT_BBA",
        "memberId": "8f6b9cef9fa104e87379d746e053ef13coba",
        "planId": "81039MP1"
      }
    },
    {
      "method": "POST",
      "url": "/api/member/lookup",
      "payload": {
        "employeeIdOrSsn": "CTP999900092",
        "groupId": "COBALT_BBA"
      }
    },
    {
      "method": "POST",
      "url": "/api/faxback/claimFaxBack",
      "payload": {
        "groupId": "COBALT_BBA",
        "divisionId": "80975",
        "memberId": "9a553ce97be637b491b273d5c428deb0coba",
        "providerTinOrNpi": "042800541",
        "serviceToDate": "07/24/2025",
        "serviceFromDate": "07/24/2025",
        "patientDob": "04/13/1980",
        "claimCoverageCode": "MED"
      }
    },
    {
      "method": "POST",
      "url": "/api/faxback/eligibilityFaxBack",
      "payload": {
        "divisionId": "81039",
        "employeeId": "X3FYQCN038TVB715NZ55FHA044",
        "groupId": "COBALT_BBA",
        "memberId": "8f6b9cef9fa104e87379d746e053ef13coba",
        "planId": "81039MP1"
      }
    },
    {
      "method": "POST",
      "url": "/api/member/sbcDoc",
      "payload": {
        "divisionId":"81039",
        "groupId":"COBALT_BBA",
        "planId":"81039MP1",
        "claimCoverageCode":"MED"
      }
    },
    {
      "method": "POST",
      "url": "/api/member/eobCard",
      "payload": {
        "memberId": "c992fbc78a9a78d48a31ef1f7be74ca0coba",
        "groupId": "COBALT_BBA",
        "divisionId": "80802",
        "employeeId": "XJVRBQ4YQYD2YH55C80VYRRMSW",
        "claimNumber": "226-0000200987-00",
        "claimCoverageCode": "DEN"
      }
    },
    {
      "method": "POST",
      "url": "/api/claim/detail",
      "payload": {
        "claimId" :"226-0000200987-00",
        "groupId":"COBALT_BBA",
        "memberId":"VNA980200006-01"
      }
    },
    {
      "method": "GET",
      "url": "/api/provider/getProviderDetailByTin",
      "payload": {
        "groupId": "COBALT_BBA",
        "tin": "631217503"
      }
    },
    {
      "method": "GET",
      "url": "/api/provider/getProviderDetailByNpi",
      "payload": {
        "groupId": "COBALT_BBA",
        "npi": "1609990290"
      }
    },
    {
      "method": "POST",
      "url": "/api/documentDelivery/sendEmail",
      "payload": {
        "groupId": "COBALT_BBA",
        "recipientEmail": "saurav.tuladhar@zakipoint.com",
        "memberId": "AVQ998400017-00",
        "documentType": "ID",
        "providerTinOrNpi": "621861198",
        "claimCoverageCode":"MED"
      }
    },
    {
      "method": "POST",
      "url": "/api/documentDelivery/sendSMS",
      "payload": {
        "groupId": "COBALT_BBA",
        "recipientPhone": "508-251-9773",
        "memberId": "AVQ998400017-00",
        "documentType": "SBC",
        "claimCoverageCode":"MED"
      }
    }
  ]
}